<annotation verified="yes">
    <folder>Annotation</folder>
    <filename>GOPR0066.MP4#t=39.733333.jpg</filename>
    <path>parts_6-PascalVOC-export/Annotations/GOPR0066.MP4#t=39.733333.jpg</path>
    <source>
        <database>Unknown</database>
    </source>
    <size>
        <width>1920</width>
        <height>1080</height>
        <depth>3</depth>
    </size>
    <segmented>0</segmented>
    <object>
    <name>wood</name>
    <pose>Unspecified</pose>
    <truncated>0</truncated>
    <difficult>0</difficult>
    <bndbox>
        <xmin>652.5231719876416</xmin>
        <ymin>57.54807692307693</ymin>
        <xmax>800.8238928939238</xmax>
        <ymax>247.43818681318683</ymax>
    </bndbox>
</object>
</annotation>
