<annotation verified="yes">
    <folder>Annotation</folder>
    <filename>GOPR0065.MP4#t=102.133333.jpg</filename>
    <path>parts_5-PascalVOC-export/Annotations/GOPR0065.MP4#t=102.133333.jpg</path>
    <source>
        <database>Unknown</database>
    </source>
    <size>
        <width>1920</width>
        <height>1080</height>
        <depth>3</depth>
    </size>
    <segmented>0</segmented>
    <object>
    <name>wood</name>
    <pose>Unspecified</pose>
    <truncated>0</truncated>
    <difficult>0</difficult>
    <bndbox>
        <xmin>607.0442842430484</xmin>
        <ymin>445.24038461538464</ymin>
        <xmax>1016.3542739443873</xmax>
        <ymax>975.3502747252747</ymax>
    </bndbox>
</object>
</annotation>
