<annotation verified="yes">
    <folder>Annotation</folder>
    <filename>GOPR0069.MP4#t=80.jpg</filename>
    <path>parts_9-PascalVOC-export/Annotations/GOPR0069.MP4#t=80.jpg</path>
    <source>
        <database>Unknown</database>
    </source>
    <size>
        <width>1920</width>
        <height>1080</height>
        <depth>3</depth>
    </size>
    <segmented>0</segmented>
    <object>
    <name>garbage</name>
    <pose>Unspecified</pose>
    <truncated>0</truncated>
    <difficult>0</difficult>
    <bndbox>
        <xmin>650.5458290422246</xmin>
        <ymin>10.07554945054945</ymin>
        <xmax>1105.3347064881566</xmax>
        <ymax>399.7458791208791</ymax>
    </bndbox>
</object>
</annotation>
