<annotation verified="yes">
    <folder>Annotation</folder>
    <filename>GOPR0060.MP4#t=255.933333.jpg</filename>
    <path>parts_2-PascalVOC-export/Annotations/GOPR0060.MP4#t=255.933333.jpg</path>
    <source>
        <database>Unknown</database>
    </source>
    <size>
        <width>1920</width>
        <height>1080</height>
        <depth>3</depth>
    </size>
    <segmented>0</segmented>
    <object>
    <name>wood</name>
    <pose>Unspecified</pose>
    <truncated>0</truncated>
    <difficult>0</difficult>
    <bndbox>
        <xmin>692.0700308959836</xmin>
        <ymin>251.39423076923077</ymin>
        <xmax>1051.946446961895</xmax>
        <ymax>544.1414835164835</ymax>
    </bndbox>
</object>
</annotation>
